owasp_security/__init__.py
owasp_security/correlation_id.py
owasp_security/metrics.py
owasp_security/rate_limiter.py
owasp_security/schema_validation.py
owasp_security/security_headers.py
owasp_security/ssrf_guard.py
python_owasp_security-0.1.1.dist-info/METADATA
python_owasp_security-0.1.1.dist-info/WHEEL
python_owasp_security-0.1.1.dist-info/top_level.txt
python_owasp_security-0.1.1.dist-info/RECORD
