Metadata-Version: 2.4
Name: python-owasp-security
Version: 0.1.1
Summary: OWASP Security Middleware and Utilities for Python APIs
Home-page: https://github.com/JhoanPragma/python-owasp-security
Author: Jhoan Pragma
Author-email: Jhoan Pragma <jhoan.gonzaleze@pragma.com.co>
License: Apache-2.0
Project-URL: Homepage, https://github.com/JhoanPragma/python-owasp-security
Project-URL: Bug Tracker, https://github.com/JhoanPragma/python-owasp-security/issues
Requires-Python: >=3.9
Requires-Dist: Flask>=3.0.0
Requires-Dist: pydantic>=2.0.0
Requires-Dist: jsonschema>=4.0.0
Requires-Dist: prometheus-client>=0.20.0
Requires-Dist: requests>=2.31.0
